dynacrop/__init__.py
dynacrop/api_handles.py
dynacrop/config.py
dynacrop/constants.py
dynacrop/exceptions.py
dynacrop/processing_request_base.py
dynacrop/sdk.py
dynacrop/attrs/__init__.py
dynacrop/attrs/async_request.py
dynacrop/attrs/polygon.py
dynacrop/attrs/processing_request.py
dynacrop/attrs/user.py
tests/__init__.py
tests/conftest.py
tests/test_polygon.py
tests/test_processing_request.py
tests/test_processing_request_result.py
tests/test_utils.py
dynacrop-0.0.3.post2.dist-info/LICENSE
dynacrop-0.0.3.post2.dist-info/METADATA
dynacrop-0.0.3.post2.dist-info/WHEEL
dynacrop-0.0.3.post2.dist-info/top_level.txt
dynacrop-0.0.3.post2.dist-info/RECORD
