Metadata-Version: 2.1
Name: dynacrop
Version: 0.0.3.post2
Summary: Python Software Development Kit library for DynaCrop API
Home-page: UNKNOWN
Author: World from Space
License: UNKNOWN
Platform: UNKNOWN
Classifier: Programming Language :: Python :: 3.7
Classifier: License :: OSI Approved :: MIT License
Classifier: Operating System :: OS Independent
Requires-Python: >=3.7
Requires-Dist: geopandas (>=0.7.0)
Requires-Dist: rasterio (>=1.0a12)
Requires-Dist: numpy (>=1.20.0)
Requires-Dist: requests (>=2.20.0)
Requires-Dist: Fiona (>=1.8.13)
